{
  "mc_story/mine_stone": 1782866201,
  "mod_mts/jumperpack": 1782866201,
  "mc_end/elytra": 1782866201,
  "mod_farmersdelight/place_skillet": 1782866201,
  "mc_story/smelt_iron": 1782866201,
  "mc_nether/summon_wither": 1782866201,
  "mc_adventure/avoid_vibration": 1782866201,
  "mc_adventure/throw_trident": 1782866201,
  "mc_nether/create_full_beacon": 1782866201,
  "mod_mts/key": 1782866201,
  "mod_moredelight/get_toast_with_egg": 1782866201,
  "mc_nether/explore_nether": 1782866201,
  "mc_nether/find_bastion": 1782866201,
  "mc_nether/charge_respawn_anchor": 1782866201,
  "mc_husbandry/ride_a_boat_with_a_goat": 1782866201,
  "mc_adventure/very_very_frightening": 1782866201,
  "mc_husbandry/feed_snifflet": 1782866201,
  "mc_adventure/two_birds_one_arrow": 1782866201,
  "mc_husbandry/silk_touch_nest": 1782866201,
  "mc_adventure/play_jukebox_in_meadows": 1782866201,
  "mc_story/enter_the_end": 1782866201,
  "mc_end/kill_dragon": 1782866201,
  "mc_husbandry/tactical_fishing": 1782866201,
  "mc_adventure/lighten_up": 1782866201,
  "mc_adventure/ol_betsy": 1782866201,
  "mc_adventure/spyglass_at_ghast": 1782866201,
  "mc_adventure/kill_all_mobs": 1782866201,
  "mc_nether/use_lodestone": 1782866201,
  "mc_adventure/summon_iron_golem": 1782866201,
  "mc_story/deflect_arrow": 1782866201,
  "mc_husbandry/fishy_business": 1782866201,
  "mc_adventure/read_power_of_chiseled_bookshelf": 1782866201,
  "mc_husbandry/leash_all_frog_variants": 1782866201,
  "mc_husbandry/tadpole_in_a_bucket": 1782866201,
  "mc_nether/brew_potion": 1782866201,
  "mc_husbandry/obtain_netherite_hoe": 1782866201,
  "mod_mts/root": 1782866201,
  "mod_mts/gunbench": 1782866201,
  "mc_adventure/trim_with_all_exclusive_armor_patterns": 1782866201,
  "mc_adventure/minecraft_trials_edition": 1782866201,
  "mod_mts/enginebench": 1782866201,
  "mc_adventure/trade_at_world_height": 1782866201,
  "mc_adventure/brush_armadillo": 1782866201,
  "mc_husbandry/axolotl_in_a_bucket": 1782866201,
  "mod_mts/jerrycan": 1782866201,
  "mc_husbandry/balanced_diet": 1782866201,
  "mc_husbandry/froglights": 1782866201,
  "mod_farmersdelight/get_fd_seed": 1782866201,
  "mod_mts/propellerbench": 1782866201,
  "mc_end/respawn_dragon": 1782866201,
  "mod_farmersdelight/get_ham": 1782866201,
  "mc_nether/obtain_blaze_rod": 1782866201,
  "mc_adventure/bullseye": 1782866201,
  "mod_farmersdelight/master_chef": 1782866201,
  "mc_husbandry/repair_wolf_armor": 1782866201,
  "mc_adventure/honey_block_slide": 1782866201,
  "mod_moredelight/get_chicken_sandwich_with_egg_and_tomato": 1782866201,
  "mc_adventure/blowback": 1782866201,
  "mod_farmersdelight/place_cooking_pot": 1782866201,
  "mc_husbandry/plant_any_sniffer_seed": 1782866201,
  "mc_adventure/root": 1782866201,
  "mc_nether/ride_strider": 1782866201,
  "mod_farmersdelight/harvest_straw": 1782866201,
  "mc_story/cure_zombie_villager": 1782866201,
  "mc_husbandry/safely_harvest_honey": 1782866201,
  "mod_mts/itembench": 1782866201,
  "mc_nether/create_beacon": 1782866201,
  "mod_farmersdelight/eat_nourishing_food": 1782866201,
  "mc_nether/uneasy_alliance": 1782866201,
  "mc_husbandry/root": 1782866201,
  "mod_mts/wheelbench": 1782866201,
  "mc_end/root": 1782866201,
  "mc_adventure/trim_with_any_armor_pattern": 1782866201,
  "mod_moredelight/root": 1782866201,
  "mc_story/obtain_armor": 1782866201,
  "mc_husbandry/plant_seed": 1782866201,
  "mc_nether/loot_bastion": 1782866201,
  "mc_story/mine_diamond": 1782866201,
  "mc_nether/obtain_crying_obsidian": 1782866201,
  "mc_adventure/shoot_arrow": 1782866201,
  "mc_story/upgrade_tools": 1782866201,
  "mod_farmersdelight/use_cutting_board": 1782866201,
  "mc_adventure/spyglass_at_dragon": 1782866201,
  "mod_farmersdelight/root": 1782866201,
  "mc_adventure/whos_the_pillager_now": 1782866201,
  "mc_adventure/fall_from_world_height": 1782866201,
  "mod_farmersdelight/harvest_ropelogged_tomato": 1782866201,
  "mod_moredelight/get_diced_potatoes_with": 1782866201,
  "mc_husbandry/remove_wolf_armor": 1782866201,
  "mc_nether/obtain_ancient_debris": 1782866201,
  "mc_husbandry/tame_an_animal": 1782866201,
  "mc_husbandry/allay_deliver_cake_to_note_block": 1782866201,
  "mc_story/enchant_item": 1782866201,
  "mod_mts/jumpercable": 1782866201,
  "mc_adventure/walk_on_powder_snow_with_leather_boots": 1782866201,
  "mc_adventure/sniper_duel": 1782866201,
  "mod_mts/seatbench": 1782866201,
  "mc_husbandry/kill_axolotl_target": 1782866201,
  "mc_nether/fast_travel": 1782866201,
  "mod_farmersdelight/get_rich_soil": 1782866201,
  "mod_farmersdelight/place_organic_compost": 1782866201,
  "mod_moredelight/get_egg_with_bacon_sandwich": 1782866201,
  "mc_adventure/overoverkill": 1782866201,
  "mc_adventure/totem_of_undying": 1782866201,
  "mod_mts/fuelpump": 1782866201,
  "mod_farmersdelight/place_campfire": 1782866201,
  "mod_moredelight/get_mashed_potatoes": 1782866201,
  "mod_farmersdelight/plant_rice": 1782866201,
  "mc_husbandry/complete_catalogue": 1782866201,
  "mod_farmersdelight/place_feast": 1782866201,
  "mod_mts/paintgun": 1782866201,
  "mod_mts/custombench": 1782866201,
  "mc_husbandry/bred_all_animals": 1782866201,
  "mc_adventure/trade": 1782866201,
  "mc_nether/ride_strider_in_overworld_lava": 1782866201,
  "mc_adventure/sleep_in_bed": 1782866201,
  "mc_adventure/kill_mob_near_sculk_catalyst": 1782866201,
  "mc_adventure/voluntary_exile": 1782866201,
  "mc_adventure/salvage_sherd": 1782866201,
  "mc_husbandry/make_a_sign_glow": 1782866201,
  "mc_nether/find_fortress": 1782866201,
  "mc_adventure/crafters_crafting_crafters": 1782866201,
  "mc_nether/netherite_armor": 1782866201,
  "mc_husbandry/wax_off": 1782866201,
  "mc_end/enter_end_gateway": 1782866201,
  "mc_story/lava_bucket": 1782866201,
  "mc_nether/return_to_sender": 1782866201,
  "mod_mts/instrumentbench": 1782866201,
  "mc_adventure/revaulting": 1782866201,
  "mod_moredelight/stone_knife": 1782866201,
  "mod_farmersdelight/use_skillet": 1782866201,
  "mc_husbandry/allay_deliver_item_to_player": 1782866201,
  "mod_farmersdelight/obtain_netherite_knife": 1782866201,
  "mod_mts/wrench": 1782866201,
  "mc_end/dragon_egg": 1782866201,
  "mc_nether/root": 1782866201,
  "mod_farmersdelight/craft_knife": 1782866201,
  "mod_moredelight/wooden_knife": 1782866201,
  "mod_mts/decorbench": 1782866201,
  "mc_adventure/who_needs_rockets": 1782866201,
  "mc_adventure/under_lock_and_key": 1782866201,
  "mc_adventure/adventuring_time": 1782866201,
  "first_launch": 1782866201,
  "mc_husbandry/breed_an_animal": 1782866201,
  "mc_end/find_end_city": 1782866201,
  "mc_adventure/lightning_rod_with_villager_no_fire": 1782866201,
  "mod_moredelight/get_omelette": 1782866201,
  "mod_mts/rtfm": 1782866201,
  "mod_mts/ticket": 1782866201,
  "mc_story/shiny_gear": 1782866201,
  "mc_husbandry/whole_pack": 1782866201,
  "mc_nether/all_effects": 1782866201,
  "mc_end/levitate": 1782866201,
  "mc_story/enter_the_nether": 1782866201,
  "mc_adventure/arbalistic": 1782866201,
  "mod_moredelight/get_cooked_rice_with": 1782866201,
  "mod_moredelight/get_creamy_pasta_with_ham": 1782866201,
  "mc_husbandry/wax_on": 1782866201,
  "mc_nether/distract_piglin": 1782866201,
  "mod_mts/vehiclebench": 1782866201,
  "mod_farmersdelight/hit_raider_with_rotten_tomato": 1782866201,
  "mod_mts/fuelhose": 1782866201,
  "mod_farmersdelight/plant_all_crops": 1782866201,
  "mc_story/follow_ender_eye": 1782866201,
  "mc_nether/get_wither_skull": 1782866201,
  "mod_mts/partscanner": 1782866201,
  "mod_farmersdelight/get_mushroom_colony": 1782866201,
  "mc_adventure/craft_decorated_pot_using_only_sherds": 1782866201,
  "mc_adventure/spyglass_at_parrot": 1782866201,
  "mc_adventure/hero_of_the_village": 1782866201,
  "mc_husbandry/obtain_sniffer_egg": 1782866201,
  "mc_story/root": 1782866201,
  "mc_story/form_obsidian": 1782866201,
  "mc_story/iron_tools": 1782866201,
  "mc_end/dragon_breath": 1782866201,
  "mc_nether/all_potions": 1782866201,
  "mc_adventure/kill_a_mob": 1782866201
}
